mkdocs_plugin_texsmith/__init__.py
mkdocs_plugin_texsmith/plugin.py
mkdocs_texsmith-0.2.1.dist-info/METADATA
mkdocs_texsmith-0.2.1.dist-info/WHEEL
mkdocs_texsmith-0.2.1.dist-info/entry_points.txt
mkdocs_texsmith-0.2.1.dist-info/licenses/LICENSE.md
mkdocs_texsmith-0.2.1.dist-info/RECORD
