Metadata-Version: 2.4
Name: mkdocs-texsmith
Version: 0.2.1
Summary: Convert MkDocs documentation to LaTeX PDF.
Project-URL: Homepage, https://github.com/yves-chevallier/mkdocs-texsmith
Author-email: Yves Chevallier <yves.chevalier@heig-vd.ch>
License-Expression: MIT
License-File: LICENSE.md
Keywords: convert,extensions,latex,markdown,mkdocs,texsmith
Classifier: Programming Language :: Python :: 3
Classifier: Programming Language :: Python :: 3 :: Only
Classifier: Programming Language :: Python :: 3.10
Classifier: Programming Language :: Python :: 3.11
Classifier: Programming Language :: Python :: 3.12
Classifier: Programming Language :: Python :: 3.13
Requires-Python: >=3.10
Requires-Dist: texsmith==0.2.1
